lacard/__init__.py
lacard-0.0.0a0.dist-info/METADATA
lacard-0.0.0a0.dist-info/WHEEL
lacard-0.0.0a0.dist-info/RECORD
